{
  "updated_at": "2026-02-11T07:28:03.441Z",
  "cards": [
    {
      "data": {
        "title": "白金貨",
        "description": "$5",
        "type": "財宝",
        "type2": "",
        "price": "$9",
        "preview": "$5",
        "credit": "Illustration: Ryan Laukat",
        "creator": "© 2022 Rio Grande Games",
        "expansionName": "繁栄",
        "boldkeys": "",
        "deckSize": 12,
        "size": "3",
        "color0": 1,
        "color1": 0,
        "traveller": "false",
        "trait": "false",
        "pictureX": "0",
        "pictureY": "0",
        "pictureZoom": "1",
        "picture": "https://wiki.dominionstrategy.com/images/1/1a/PlatinumArt.jpg",
        "expansion": "https://wiki.dominionstrategy.com/images/f/fb/Prosperity_icon.png",
        "customIcon": "",
        "edition": "",
        "official": true
      },
      "images": {
        "illustration": null,
        "expansion": null,
        "customIcon": null
      },
      "timestamp": 1770794883440
    },
    {
      "data": {
        "title": "植民地",
        "description": "10%",
        "type": "勝利点",
        "type2": "",
        "price": "$11",
        "preview": "",
        "credit": "Illustration: Martin Hoffmann",
        "creator": "© 2022 Rio Grande Games",
        "expansionName": "繁栄",
        "boldkeys": "",
        "deckSize": 12,
        "size": "3",
        "color0": 2,
        "color1": 0,
        "traveller": "false",
        "trait": "false",
        "pictureX": "0",
        "pictureY": "0",
        "pictureZoom": "1",
        "picture": "https://wiki.dominionstrategy.com/images/2/2d/ColonyArt.jpg",
        "expansion": "https://wiki.dominionstrategy.com/images/f/fb/Prosperity_icon.png",
        "customIcon": "",
        "edition": "",
        "official": true
      },
      "images": {
        "illustration": null,
        "expansion": null,
        "customIcon": null
      },
      "timestamp": 1770794883441
    },
    {
      "data": {
        "title": "望楼",
        "description": "手札が6枚になるまでカードを引く。\n-\nあなたがカード1枚を獲得するとき、あなたの手札からこれを公開してもよい。そうした場合そのカードを廃棄するか、あなたのデッキの上に置く。",
        "type": "アクション-リアクション",
        "type2": "",
        "price": "$3",
        "preview": "",
        "credit": "Illustration: Rick Hershey",
        "creator": "© 2022 Rio Grande Games",
        "expansionName": "繁栄",
        "boldkeys": "",
        "deckSize": "",
        "size": "0",
        "color0": 3,
        "color1": 0,
        "traveller": "false",
        "trait": "false",
        "pictureX": "0",
        "pictureY": "0",
        "pictureZoom": "1",
        "picture": "https://wiki.dominionstrategy.com/images/e/e1/WatchtowerArt.jpg",
        "expansion": "https://wiki.dominionstrategy.com/images/f/fb/Prosperity_icon.png",
        "customIcon": "",
        "edition": "",
        "official": true
      },
      "images": {
        "illustration": null,
        "expansion": null,
        "customIcon": null
      },
      "timestamp": 1770794883442
    },
    {
      "data": {
        "title": "金床",
        "description": "$1\nあなたは財宝カード1枚を捨て札にしてもよい。そうした場合コスト$4以下のカード1枚を獲得する。",
        "type": "財宝",
        "type2": "",
        "price": "$3",
        "preview": "$1",
        "credit": "Illustration: Jessi J",
        "creator": "© 2022 Rio Grande Games",
        "expansionName": "繁栄",
        "boldkeys": "",
        "deckSize": "",
        "size": "0",
        "color0": 1,
        "color1": 0,
        "traveller": "false",
        "trait": "false",
        "pictureX": "0",
        "pictureY": "0",
        "pictureZoom": "1",
        "picture": "https://wiki.dominionstrategy.com/images/7/77/AnvilArt.jpg",
        "expansion": "https://wiki.dominionstrategy.com/images/f/fb/Prosperity_icon.png",
        "customIcon": "",
        "edition": "【二版】",
        "official": true
      },
      "images": {
        "illustration": null,
        "expansion": null,
        "customIcon": null
      },
      "timestamp": 1770794883443
    },
    {
      "data": {
        "title": "記念碑",
        "description": "+$2\n+1%",
        "type": "アクション",
        "type2": "",
        "price": "$4",
        "preview": "",
        "credit": "Illustration: Julien Delval",
        "creator": "© 2022 Rio Grande Games",
        "expansionName": "繁栄",
        "boldkeys": "",
        "deckSize": "",
        "size": "0",
        "color0": 0,
        "color1": 0,
        "traveller": "false",
        "trait": "false",
        "pictureX": "0",
        "pictureY": "0",
        "pictureZoom": "1",
        "picture": "https://wiki.dominionstrategy.com/images/d/d5/MonumentArt.jpg",
        "expansion": "https://wiki.dominionstrategy.com/images/f/fb/Prosperity_icon.png",
        "customIcon": "",
        "edition": "",
        "official": true
      },
      "images": {
        "illustration": null,
        "expansion": null,
        "customIcon": null
      },
      "timestamp": 1770794883444
    },
    {
      "data": {
        "title": "司教",
        "description": "+$1\n+1%\nあなたの手札からカード1枚を廃棄する。そのコスト$2につき(端数切捨て)+1%。他のプレイヤーは全員、自分の手札からカード1枚を廃棄してもよい。",
        "type": "アクション",
        "type2": "",
        "price": "$4",
        "preview": "",
        "credit": "Illustration: Rom",
        "creator": "© 2022 Rio Grande Games",
        "expansionName": "繁栄",
        "boldkeys": "",
        "deckSize": "",
        "size": "0",
        "color0": 0,
        "color1": 0,
        "traveller": "false",
        "trait": "false",
        "pictureX": "0",
        "pictureY": "0",
        "pictureZoom": "1",
        "picture": "https://wiki.dominionstrategy.com/images/4/48/BishopArt.jpg",
        "expansion": "https://wiki.dominionstrategy.com/images/f/fb/Prosperity_icon.png",
        "customIcon": "",
        "edition": "",
        "official": true
      },
      "images": {
        "illustration": null,
        "expansion": null,
        "customIcon": null
      },
      "timestamp": 1770794883445
    },
    {
      "data": {
        "title": "労働者の村",
        "description": "+1 カードを引く\n+2 アクション\n+1 カードを購入",
        "type": "アクション",
        "type2": "",
        "price": "$4",
        "preview": "",
        "credit": "Illustration: Claus Stephan",
        "creator": "© 2022 Rio Grande Games",
        "expansionName": "繁栄",
        "boldkeys": "",
        "deckSize": "",
        "size": "0",
        "color0": 0,
        "color1": 0,
        "traveller": "false",
        "trait": "false",
        "pictureX": "0",
        "pictureY": "0",
        "pictureZoom": "1",
        "picture": "https://wiki.dominionstrategy.com/images/5/5c/Worker%27s_VillageArt.jpg",
        "expansion": "https://wiki.dominionstrategy.com/images/f/fb/Prosperity_icon.png",
        "customIcon": "",
        "edition": "",
        "official": true
      },
      "images": {
        "illustration": null,
        "expansion": null,
        "customIcon": null
      },
      "timestamp": 1770794883446
    },
    {
      "data": {
        "title": "書記",
        "description": "+$2\n手札が5枚以上ある他のプレイヤーは全員、その中の1枚を自分のデッキの上に置く。\n-\nあなたのターンの開始時、あなたは手札からこれを使用してもよい。",
        "type": "アクション-アタック-リアクション",
        "type2": "",
        "price": "$4",
        "preview": "",
        "credit": "Illustration: Harald Lieske",
        "creator": "© 2022 Rio Grande Games",
        "expansionName": "繁栄",
        "boldkeys": "",
        "deckSize": "",
        "size": "0",
        "color0": 3,
        "color1": 0,
        "traveller": "false",
        "trait": "false",
        "pictureX": "0",
        "pictureY": "0",
        "pictureZoom": "1",
        "picture": "https://wiki.dominionstrategy.com/images/a/a1/ClerkArt.jpg",
        "expansion": "https://wiki.dominionstrategy.com/images/f/fb/Prosperity_icon.png",
        "customIcon": "",
        "edition": "【二版】",
        "official": true
      },
      "images": {
        "illustration": null,
        "expansion": null,
        "customIcon": null
      },
      "timestamp": 1770794883447
    },
    {
      "data": {
        "title": "石切場",
        "description": "$1\nこのターン、アクションカードのコストは$2少なくなる。",
        "type": "財宝",
        "type2": "",
        "price": "$4",
        "preview": "$1",
        "credit": "Illustration: Brian Brinlee",
        "creator": "© 2022 Rio Grande Games",
        "expansionName": "繁栄",
        "boldkeys": "",
        "deckSize": "",
        "size": "0",
        "color0": 1,
        "color1": 0,
        "traveller": "false",
        "trait": "false",
        "pictureX": "0",
        "pictureY": "0",
        "pictureZoom": "1",
        "picture": "https://wiki.dominionstrategy.com/images/6/6d/QuarryArt.jpg",
        "expansion": "https://wiki.dominionstrategy.com/images/f/fb/Prosperity_icon.png",
        "customIcon": "",
        "edition": "",
        "official": true
      },
      "images": {
        "illustration": null,
        "expansion": null,
        "customIcon": null
      },
      "timestamp": 1770794883448
    },
    {
      "data": {
        "title": "出資",
        "description": "あなたの手札からカード1枚を廃棄する。次のうち1つを選ぶ；「+$1」；「これを廃棄して自分の手札を公開し、手札の異なる名前の財宝カード1枚につき+1%」",
        "type": "財宝",
        "type2": "",
        "price": "$4",
        "preview": "$?",
        "credit": "Illustration: Marco Primo",
        "creator": "© 2022 Rio Grande Games",
        "expansionName": "繁栄",
        "boldkeys": "",
        "deckSize": "",
        "size": "0",
        "color0": 1,
        "color1": 0,
        "traveller": "false",
        "trait": "false",
        "pictureX": "0",
        "pictureY": "0",
        "pictureZoom": "1",
        "picture": "https://wiki.dominionstrategy.com/images/e/e2/InvestmentArt.jpg",
        "expansion": "https://wiki.dominionstrategy.com/images/f/fb/Prosperity_icon.png",
        "customIcon": "",
        "edition": "【二版】",
        "official": true
      },
      "images": {
        "illustration": null,
        "expansion": null,
        "customIcon": null
      },
      "timestamp": 1770794883449
    },
    {
      "data": {
        "title": "ティアラ",
        "description": "+1 カードを購入\nこのターン、あなたがカードを獲得するとき、そのカードをあなたのデッキの上に置いてもよい。あなたは手札から1枚の財宝カードを2回使用してもよい。",
        "type": "財宝",
        "type2": "",
        "price": "$4",
        "preview": "",
        "credit": "Illustration: Lynell Ingram",
        "creator": "© 2022 Rio Grande Games",
        "expansionName": "繁栄",
        "boldkeys": "",
        "deckSize": "",
        "size": "0",
        "color0": 1,
        "color1": 0,
        "traveller": "false",
        "trait": "false",
        "pictureX": "0",
        "pictureY": "0",
        "pictureZoom": "1",
        "picture": "https://wiki.dominionstrategy.com/images/b/b6/TiaraArt.jpg",
        "expansion": "https://wiki.dominionstrategy.com/images/f/fb/Prosperity_icon.png",
        "customIcon": "",
        "edition": "【二版】",
        "official": true
      },
      "images": {
        "illustration": null,
        "expansion": null,
        "customIcon": null
      },
      "timestamp": 1770794883450
    },
    {
      "data": {
        "title": "造幣所",
        "description": "あなたは手札から財宝カード1枚を公開してもよい。それと同一のカード1枚を獲得する。\n-\nあなたがこれを獲得するとき、あなたの場に出ている持続以外の財宝カードすべてを廃棄する。",
        "type": "アクション",
        "type2": "",
        "price": "$5",
        "preview": "",
        "credit": "Illustration: Kim Feigenbaum",
        "creator": "© 2022 Rio Grande Games",
        "expansionName": "繁栄",
        "boldkeys": "",
        "deckSize": "",
        "size": "0",
        "color0": 0,
        "color1": 0,
        "traveller": "false",
        "trait": "false",
        "pictureX": "0",
        "pictureY": "0",
        "pictureZoom": "1",
        "picture": "https://wiki.dominionstrategy.com/images/b/b9/MintArt.jpg",
        "expansion": "https://wiki.dominionstrategy.com/images/f/fb/Prosperity_icon.png",
        "customIcon": "",
        "edition": "",
        "official": true
      },
      "images": {
        "illustration": null,
        "expansion": null,
        "customIcon": null
      },
      "timestamp": 1770794883451
    },
    {
      "data": {
        "title": "都市",
        "description": "+1 カードを引く\n+2 アクション\nカードが1枚も残っていないサプライの山札が1つ以上ある場合、+1 カードを引く。2つ以上ある場合、+1 カードを購入と+$1。",
        "type": "アクション",
        "type2": "",
        "price": "$5",
        "preview": "",
        "credit": "Illustration: Marco Primo",
        "creator": "© 2022 Rio Grande Games",
        "expansionName": "繁栄",
        "boldkeys": "",
        "deckSize": "",
        "size": "0",
        "color0": 0,
        "color1": 0,
        "traveller": "false",
        "trait": "false",
        "pictureX": "0",
        "pictureY": "0",
        "pictureZoom": "1",
        "picture": "https://wiki.dominionstrategy.com/images/3/37/CityArt.jpg",
        "expansion": "https://wiki.dominionstrategy.com/images/f/fb/Prosperity_icon.png",
        "customIcon": "",
        "edition": "",
        "official": true
      },
      "images": {
        "illustration": null,
        "expansion": null,
        "customIcon": null
      },
      "timestamp": 1770794883452
    },
    {
      "data": {
        "title": "保管庫",
        "description": "+2 カードを引く\n好きな枚数のカードを捨て札にして、捨て札にしたカード1枚につき＋$1。他のプレイヤーは全員、カード2枚を捨て札にしてもよい。そうした場合、そのプレイヤーはカード1枚を引く。",
        "type": "アクション",
        "type2": "",
        "price": "$5",
        "preview": "",
        "credit": "Illustration: Alex Drummond",
        "creator": "© 2022 Rio Grande Games",
        "expansionName": "繁栄",
        "boldkeys": "",
        "deckSize": "",
        "size": "0",
        "color0": 0,
        "color1": 0,
        "traveller": "false",
        "trait": "false",
        "pictureX": "0",
        "pictureY": "0",
        "pictureZoom": "1",
        "picture": "https://wiki.dominionstrategy.com/images/4/49/VaultArt.jpg",
        "expansion": "https://wiki.dominionstrategy.com/images/f/fb/Prosperity_icon.png",
        "customIcon": "",
        "edition": "",
        "official": true
      },
      "images": {
        "illustration": null,
        "expansion": null,
        "customIcon": null
      },
      "timestamp": 1770794883453
    },
    {
      "data": {
        "title": "有力者",
        "description": "あなたの手札を公開する。その中の財宝カード1枚につき、+1 カードを引く。",
        "type": "アクション",
        "type2": "",
        "price": "$5",
        "preview": "",
        "credit": "Illustration: Harald Lieske",
        "creator": "© 2022 Rio Grande Games",
        "expansionName": "繁栄",
        "boldkeys": "",
        "deckSize": "",
        "size": "0",
        "color0": 0,
        "color1": 0,
        "traveller": "false",
        "trait": "false",
        "pictureX": "0",
        "pictureY": "0",
        "pictureZoom": "1",
        "picture": "https://wiki.dominionstrategy.com/images/4/4b/MagnateArt.jpg",
        "expansion": "https://wiki.dominionstrategy.com/images/f/fb/Prosperity_icon.png",
        "customIcon": "",
        "edition": "【二版】",
        "official": true
      },
      "images": {
        "illustration": null,
        "expansion": null,
        "customIcon": null
      },
      "timestamp": 1770794883454
    },
    {
      "data": {
        "title": "山師",
        "description": "+$3\n他のプレイヤーは全員、「呪い」1枚を獲得する。\n-\nこれを使うゲームでは、「呪い」1枚は$1の価値がある財宝カードでもある。",
        "type": "アクション-アタック",
        "type2": "",
        "price": "$5",
        "preview": "",
        "credit": "Illustration: Franz Vohwinkel",
        "creator": "© 2022 Rio Grande Games",
        "expansionName": "繁栄",
        "boldkeys": "",
        "deckSize": "",
        "size": "0",
        "color0": 0,
        "color1": 0,
        "traveller": "false",
        "trait": "false",
        "pictureX": "0",
        "pictureY": "0",
        "pictureZoom": "1",
        "picture": "https://wiki.dominionstrategy.com/images/0/0d/CharlatanArt.jpg",
        "expansion": "https://wiki.dominionstrategy.com/images/f/fb/Prosperity_icon.png",
        "customIcon": "",
        "edition": "【二版】",
        "official": true
      },
      "images": {
        "illustration": null,
        "expansion": null,
        "customIcon": null
      },
      "timestamp": 1770794883455
    },
    {
      "data": {
        "title": "大衆",
        "description": "+3 カードを引く\n他のプレイヤーは全員、自分のデッキの上から3枚を公開し、その中のアクションと財宝カードを捨て札にし、残りのカードを自分の好きな順番でデッキの上に戻す。",
        "type": "アクション-アタック",
        "type2": "",
        "price": "$5",
        "preview": "",
        "credit": "Illustration: RC Torres",
        "creator": "© 2022 Rio Grande Games",
        "expansionName": "繁栄",
        "boldkeys": "",
        "deckSize": "",
        "size": "0",
        "color0": 0,
        "color1": 0,
        "traveller": "false",
        "trait": "false",
        "pictureX": "0",
        "pictureY": "0",
        "pictureZoom": "1",
        "picture": "https://wiki.dominionstrategy.com/images/1/1b/RabbleArt.jpg",
        "expansion": "https://wiki.dominionstrategy.com/images/f/fb/Prosperity_icon.png",
        "customIcon": "",
        "edition": "",
        "official": true
      },
      "images": {
        "illustration": null,
        "expansion": null,
        "customIcon": null
      },
      "timestamp": 1770794883456
    },
    {
      "data": {
        "title": "収集品",
        "description": "$2\n+1 カードを購入\nこのターン、あなたがアクションカード1枚を獲得するとき、+1%。",
        "type": "財宝",
        "type2": "",
        "price": "$5",
        "preview": "$2",
        "credit": "Illustration: Franz Vohwinkel",
        "creator": "© 2022 Rio Grande Games",
        "expansionName": "繁栄",
        "boldkeys": "",
        "deckSize": "",
        "size": "0",
        "color0": 1,
        "color1": 0,
        "traveller": "false",
        "trait": "false",
        "pictureX": "0",
        "pictureY": "0",
        "pictureZoom": "1",
        "picture": "https://wiki.dominionstrategy.com/images/f/f6/CollectionArt.jpg",
        "expansion": "https://wiki.dominionstrategy.com/images/f/fb/Prosperity_icon.png",
        "customIcon": "",
        "edition": "【二版】",
        "official": true
      },
      "images": {
        "illustration": null,
        "expansion": null,
        "customIcon": null
      },
      "timestamp": 1770794883457
    },
    {
      "data": {
        "title": "水晶球",
        "description": "$1\nあなたのデッキの一番上のカードを見る。あなたはそれを廃棄しても、捨て札にしても、そのカードがアクションまたは財宝カードの場合は使用してもよい。",
        "type": "財宝",
        "type2": "",
        "price": "$5",
        "preview": "$1",
        "credit": "Illustration: Marco Primo",
        "creator": "© 2022 Rio Grande Games",
        "expansionName": "繁栄",
        "boldkeys": "",
        "deckSize": "",
        "size": "0",
        "color0": 1,
        "color1": 0,
        "traveller": "false",
        "trait": "false",
        "pictureX": "0",
        "pictureY": "0",
        "pictureZoom": "1",
        "picture": "https://wiki.dominionstrategy.com/images/3/38/Crystal_BallArt.jpg",
        "expansion": "https://wiki.dominionstrategy.com/images/f/fb/Prosperity_icon.png",
        "customIcon": "",
        "edition": "【二版】",
        "official": true
      },
      "images": {
        "illustration": null,
        "expansion": null,
        "customIcon": null
      },
      "timestamp": 1770794883458
    },
    {
      "data": {
        "title": "軍用金",
        "description": "あなたの左隣のプレイヤーはカード1枚を指定する。このターン「軍用金」で指定されていないコスト$5以下のカード1枚を獲得する。",
        "type": "財宝",
        "type2": "",
        "price": "$5",
        "preview": "",
        "credit": "Illustration: Lynell Ingram",
        "creator": "© 2022 Rio Grande Games",
        "expansionName": "繁栄",
        "boldkeys": "",
        "deckSize": "",
        "size": "0",
        "color0": 1,
        "color1": 0,
        "traveller": "false",
        "trait": "false",
        "pictureX": "0",
        "pictureY": "0",
        "pictureZoom": "1",
        "picture": "https://wiki.dominionstrategy.com/images/0/09/War_ChestArt.jpg",
        "expansion": "https://wiki.dominionstrategy.com/images/f/fb/Prosperity_icon.png",
        "customIcon": "",
        "edition": "【二版】",
        "official": true
      },
      "images": {
        "illustration": null,
        "expansion": null,
        "customIcon": null
      },
      "timestamp": 1770794883459
    },
    {
      "data": {
        "title": "大市場",
        "description": "+1 カードを引く\n+1 アクション\n+1 カードを購入\n+$2\n\n-\nあなたは「銅貨」を場に出している場合、このカードを購入できない。",
        "type": "アクション",
        "type2": "",
        "price": "$6*",
        "preview": "",
        "credit": "Illustration: Marcel-André Casasola Merkle",
        "creator": "© 2022 Rio Grande Games",
        "expansionName": "繁栄",
        "boldkeys": "",
        "deckSize": "",
        "size": "0",
        "color0": 0,
        "color1": 0,
        "traveller": "false",
        "trait": "false",
        "pictureX": "0",
        "pictureY": "0",
        "pictureZoom": "1",
        "picture": "https://wiki.dominionstrategy.com/images/c/cc/Grand_MarketArt.jpg",
        "expansion": "https://wiki.dominionstrategy.com/images/f/fb/Prosperity_icon.png",
        "customIcon": "",
        "edition": "",
        "official": true
      },
      "images": {
        "illustration": null,
        "expansion": null,
        "customIcon": null
      },
      "timestamp": 1770794883460
    },
    {
      "data": {
        "title": "隠し財産",
        "description": "$2\nこのターン、あなたが勝利点カードを獲得するとき、それが購入によるものの場合、「金貨」1枚を獲得する。",
        "type": "財宝",
        "type2": "",
        "price": "$6",
        "preview": "$2",
        "credit": "Illustration: Colin Throm",
        "creator": "© 2022 Rio Grande Games",
        "expansionName": "繁栄",
        "boldkeys": "",
        "deckSize": "",
        "size": "0",
        "color0": 1,
        "color1": 0,
        "traveller": "false",
        "trait": "false",
        "pictureX": "0",
        "pictureY": "0",
        "pictureZoom": "1",
        "picture": "https://wiki.dominionstrategy.com/images/e/ea/HoardArt.jpg",
        "expansion": "https://wiki.dominionstrategy.com/images/f/fb/Prosperity_icon.png",
        "customIcon": "",
        "edition": "",
        "official": true
      },
      "images": {
        "illustration": null,
        "expansion": null,
        "customIcon": null
      },
      "timestamp": 1770794883461
    },
    {
      "data": {
        "title": "拡張",
        "description": "あなたの手札からカード1枚を廃棄する。そのカードよりコストが最大$3多いカード1枚を獲得する。",
        "type": "アクション",
        "type2": "",
        "price": "$7",
        "preview": "",
        "credit": "Illustration: Ryan Laukat",
        "creator": "© 2022 Rio Grande Games",
        "expansionName": "繁栄",
        "boldkeys": "",
        "deckSize": "",
        "size": "0",
        "color0": 0,
        "color1": 0,
        "traveller": "false",
        "trait": "false",
        "pictureX": "0",
        "pictureY": "0",
        "pictureZoom": "1",
        "picture": "https://wiki.dominionstrategy.com/images/0/0a/ExpandArt.jpg",
        "expansion": "https://wiki.dominionstrategy.com/images/f/fb/Prosperity_icon.png",
        "customIcon": "",
        "edition": "",
        "official": true
      },
      "images": {
        "illustration": null,
        "expansion": null,
        "customIcon": null
      },
      "timestamp": 1770794883462
    },
    {
      "data": {
        "title": "宮廷",
        "description": "あなたの手札からアクションカード1枚を3回使用してもよい。",
        "type": "アクション",
        "type2": "",
        "price": "$7",
        "preview": "",
        "credit": "Illustration: Dennis Lohausen",
        "creator": "© 2022 Rio Grande Games",
        "expansionName": "繁栄",
        "boldkeys": "",
        "deckSize": "",
        "size": "0",
        "color0": 0,
        "color1": 0,
        "traveller": "false",
        "trait": "false",
        "pictureX": "0",
        "pictureY": "0",
        "pictureZoom": "1",
        "picture": "https://wiki.dominionstrategy.com/images/d/d4/King%27s_CourtArt.jpg",
        "expansion": "https://wiki.dominionstrategy.com/images/f/fb/Prosperity_icon.png",
        "customIcon": "",
        "edition": "",
        "official": true
      },
      "images": {
        "illustration": null,
        "expansion": null,
        "customIcon": null
      },
      "timestamp": 1770794883463
    },
    {
      "data": {
        "title": "鍛造",
        "description": "あなたの手札から好きな枚数のカードを廃棄する。廃棄したカードの$コストの合計と同じコストのカード1枚を獲得する。",
        "type": "アクション",
        "type2": "",
        "price": "$7",
        "preview": "",
        "credit": "Illustration: Martin Hoffmann",
        "creator": "© 2022 Rio Grande Games",
        "expansionName": "繁栄",
        "boldkeys": "",
        "deckSize": "",
        "size": "0",
        "color0": 0,
        "color1": 0,
        "traveller": "false",
        "trait": "false",
        "pictureX": "0",
        "pictureY": "0",
        "pictureZoom": "1",
        "picture": "https://wiki.dominionstrategy.com/images/3/35/ForgeArt.jpg",
        "expansion": "https://wiki.dominionstrategy.com/images/f/fb/Prosperity_icon.png",
        "customIcon": "",
        "edition": "",
        "official": true
      },
      "images": {
        "illustration": null,
        "expansion": null,
        "customIcon": null
      },
      "timestamp": 1770794883464
    },
    {
      "data": {
        "title": "銀行",
        "description": "あなたが場に出している(このカードを含む)財宝カード1枚につき+$1。",
        "type": "財宝",
        "type2": "",
        "price": "$7",
        "preview": "$?",
        "credit": "Illustration: Jason Snair",
        "creator": "© 2022 Rio Grande Games",
        "expansionName": "繁栄",
        "boldkeys": "",
        "deckSize": "",
        "size": "0",
        "color0": 1,
        "color1": 0,
        "traveller": "false",
        "trait": "false",
        "pictureX": "0",
        "pictureY": "0",
        "pictureZoom": "1",
        "picture": "https://wiki.dominionstrategy.com/images/8/80/BankArt.jpg",
        "expansion": "https://wiki.dominionstrategy.com/images/f/fb/Prosperity_icon.png",
        "customIcon": "",
        "edition": "",
        "official": true
      },
      "images": {
        "illustration": null,
        "expansion": null,
        "customIcon": null
      },
      "timestamp": 1770794883465
    },
    {
      "data": {
        "title": "行商人",
        "description": "+1 カードを引く\n+1 アクション\n+$1\n\n-\nプレイヤーの購入フェイズの間、このカードのコストはそのプレイヤーが場に出しているアクションカード1枚につき$2少なくなる。",
        "type": "アクション",
        "type2": "",
        "price": "$8*",
        "preview": "",
        "credit": "Illustration: Joshua Stewart",
        "creator": "© 2022 Rio Grande Games",
        "expansionName": "繁栄",
        "boldkeys": "",
        "deckSize": "",
        "size": "0",
        "color0": 0,
        "color1": 0,
        "traveller": "false",
        "trait": "false",
        "pictureX": "0",
        "pictureY": "0",
        "pictureZoom": "1",
        "picture": "https://wiki.dominionstrategy.com/images/9/9f/PeddlerArt.jpg",
        "expansion": "https://wiki.dominionstrategy.com/images/f/fb/Prosperity_icon.png",
        "customIcon": "",
        "edition": "",
        "official": true
      },
      "images": {
        "illustration": null,
        "expansion": null,
        "customIcon": null
      },
      "timestamp": 1770794883466
    },
    {
      "data": {
        "title": "交易路",
        "description": "+1 購入\n手札1枚を廃棄する。交易路マットの上にある交易路トークン1枚につき+$1。\n-\n準備：勝利点カードのサプライの山すべての上に交易路トークン1枚を追加する。その山のカード1枚を獲得したとき、交易路トークンを交易路マットの上に移動する。",
        "type": "アクション",
        "type2": "",
        "price": "$3",
        "preview": "",
        "credit": "Illustration: Harald Lieske",
        "creator": "© 2017 Rio Grande Games",
        "expansionName": "繁栄",
        "boldkeys": "",
        "deckSize": "",
        "size": "0",
        "color0": 0,
        "color1": 0,
        "traveller": "false",
        "trait": "false",
        "pictureX": "0",
        "pictureY": "0",
        "pictureZoom": "1",
        "picture": "https://wiki.dominionstrategy.com/images/3/35/Trade_RouteArt.jpg",
        "expansion": "https://wiki.dominionstrategy.com/images/5/5e/Prosperity_old_icon.png",
        "customIcon": "",
        "edition": "【削除】",
        "official": true
      },
      "images": {
        "illustration": null,
        "expansion": null,
        "customIcon": null
      },
      "timestamp": 1770794883467
    },
    {
      "data": {
        "title": "借金",
        "description": "$1\nこのカードを使うとき、あなたの山札を財宝カードが公開されるまで上から公開し、その財宝カードを捨て札にするか廃棄する。他の公開したカードは捨て札にする。",
        "type": "財宝",
        "type2": "",
        "price": "$3",
        "preview": "$1",
        "credit": "Illustration: Simon Jannerland",
        "creator": "© 2020 Rio Grande Games",
        "expansionName": "繁栄",
        "boldkeys": "",
        "deckSize": "",
        "size": "0",
        "color0": 1,
        "color1": 0,
        "traveller": "false",
        "trait": "false",
        "pictureX": "0",
        "pictureY": "0",
        "pictureZoom": "1",
        "picture": "https://wiki.dominionstrategy.com/images/3/3a/LoanArt.jpg",
        "expansion": "https://wiki.dominionstrategy.com/images/5/5e/Prosperity_old_icon.png",
        "customIcon": "",
        "edition": "【削除】",
        "official": true
      },
      "images": {
        "illustration": null,
        "expansion": null,
        "customIcon": null
      },
      "timestamp": 1770794883468
    },
    {
      "data": {
        "title": "護符",
        "description": "$1\n\n-\nこのカードが場に出ているかぎり、あなたがコスト$4以下の勝利点以外のカード1枚を購入するとき、そのカードと同じカード1枚を獲得する。",
        "type": "財宝",
        "type2": "",
        "price": "$4",
        "preview": "$1",
        "credit": "Illustration: Eric J Carter",
        "creator": "© 2020 Rio Grande Games",
        "expansionName": "繁栄",
        "boldkeys": "",
        "deckSize": "",
        "size": "0",
        "color0": 1,
        "color1": 0,
        "traveller": "false",
        "trait": "false",
        "pictureX": "0",
        "pictureY": "0",
        "pictureZoom": "1",
        "picture": "https://wiki.dominionstrategy.com/images/d/de/TalismanArt.jpg",
        "expansion": "https://wiki.dominionstrategy.com/images/5/5e/Prosperity_old_icon.png",
        "customIcon": "",
        "edition": "【削除】",
        "official": true
      },
      "images": {
        "illustration": null,
        "expansion": null,
        "customIcon": null
      },
      "timestamp": 1770794883469
    },
    {
      "data": {
        "title": "会計所",
        "description": "あなたの捨て札のカードすべてを確認し、その中から好きな枚数の銅貨カードを公開し、それをあなたの手札に加える。",
        "type": "アクション",
        "type2": "",
        "price": "$5",
        "preview": "",
        "credit": "Illustration: Matthias Catrein",
        "creator": "© 2017 Rio Grande Games",
        "expansionName": "繁栄",
        "boldkeys": "",
        "deckSize": "",
        "size": "0",
        "color0": 0,
        "color1": 0,
        "traveller": "false",
        "trait": "false",
        "pictureX": "0",
        "pictureY": "0",
        "pictureZoom": "1",
        "picture": "https://wiki.dominionstrategy.com/images/9/9c/Counting_HouseArt.jpg",
        "expansion": "https://wiki.dominionstrategy.com/images/5/5e/Prosperity_old_icon.png",
        "customIcon": "",
        "edition": "【削除】",
        "official": true
      },
      "images": {
        "illustration": null,
        "expansion": null,
        "customIcon": null
      },
      "timestamp": 1770794883471
    },
    {
      "data": {
        "title": "香具師",
        "description": "+$2\n他のプレイヤーは全員、呪いカード1枚を捨て札にしてもよい。そうしない場合、呪いカード1枚と銅貨1枚を獲得する。",
        "type": "アクション-アタック",
        "type2": "",
        "price": "$5",
        "preview": "",
        "credit": "Illustration: Kieron O'Gorman",
        "creator": "© 2019 Rio Grande Games",
        "expansionName": "繁栄",
        "boldkeys": "",
        "deckSize": "",
        "size": "0",
        "color0": 0,
        "color1": 0,
        "traveller": "false",
        "trait": "false",
        "pictureX": "0",
        "pictureY": "0",
        "pictureZoom": "1",
        "picture": "https://wiki.dominionstrategy.com/images/0/0d/MountebankArt.jpg",
        "expansion": "https://wiki.dominionstrategy.com/images/5/5e/Prosperity_old_icon.png",
        "customIcon": "",
        "edition": "【削除】",
        "official": true
      },
      "images": {
        "illustration": null,
        "expansion": null,
        "customIcon": null
      },
      "timestamp": 1770794883472
    },
    {
      "data": {
        "title": "玉璽",
        "description": "$2\n\n-\nこのカードが場に出ているかぎり、あなたがカード1枚を獲得するとき、そのカードを自分の山札の一番上に置いてもよい。",
        "type": "財宝",
        "type2": "",
        "price": "$5",
        "preview": "$2",
        "credit": "Illustration: Jason Slavin",
        "creator": "© 2020 Rio Grande Games",
        "expansionName": "繁栄",
        "boldkeys": "",
        "deckSize": "",
        "size": "0",
        "color0": 1,
        "color1": 0,
        "traveller": "false",
        "trait": "false",
        "pictureX": "0",
        "pictureY": "0",
        "pictureZoom": "1",
        "picture": "https://wiki.dominionstrategy.com/images/3/38/Royal_SealArt.jpg",
        "expansion": "https://wiki.dominionstrategy.com/images/5/5e/Prosperity_old_icon.png",
        "customIcon": "",
        "edition": "【削除】",
        "official": true
      },
      "images": {
        "illustration": null,
        "expansion": null,
        "customIcon": null
      },
      "timestamp": 1770794883473
    },
    {
      "data": {
        "title": "禁制品",
        "description": "$3\n+1 カードを購入\nこのカードを使うとき、あなたの左隣のプレイヤーはカード1枚を指定する。このターン、あなたは指定されたカードを購入できない。",
        "type": "財宝",
        "type2": "",
        "price": "$5",
        "preview": "$3",
        "credit": "Illustration: RC Torres",
        "creator": "© 2020 Rio Grande Games",
        "expansionName": "繁栄",
        "boldkeys": "",
        "deckSize": "",
        "size": "0",
        "color0": 1,
        "color1": 0,
        "traveller": "false",
        "trait": "false",
        "pictureX": "0",
        "pictureY": "0",
        "pictureZoom": "1",
        "picture": "https://wiki.dominionstrategy.com/images/0/0a/ContrabandArt.jpg",
        "expansion": "https://wiki.dominionstrategy.com/images/5/5e/Prosperity_old_icon.png",
        "customIcon": "",
        "edition": "【削除】",
        "official": true
      },
      "images": {
        "illustration": null,
        "expansion": null,
        "customIcon": null
      },
      "timestamp": 1770794883474
    },
    {
      "data": {
        "title": "投機",
        "description": "$1\nこのカードを使うとき、あなたの山札を財宝カードが公開されるまで上から公開し、その財宝カードを場に出す。残りの公開したカードは捨て札にする。",
        "type": "財宝",
        "type2": "",
        "price": "$5",
        "preview": "$1",
        "credit": "Illustration: Lee Smith",
        "creator": "© 2020 Rio Grande Games",
        "expansionName": "繁栄",
        "boldkeys": "",
        "deckSize": "",
        "size": "0",
        "color0": 1,
        "color1": 0,
        "traveller": "false",
        "trait": "false",
        "pictureX": "0",
        "pictureY": "0",
        "pictureZoom": "1",
        "picture": "https://wiki.dominionstrategy.com/images/e/e3/VentureArt.jpg",
        "expansion": "https://wiki.dominionstrategy.com/images/5/5e/Prosperity_old_icon.png",
        "customIcon": "",
        "edition": "【削除】",
        "official": true
      },
      "images": {
        "illustration": null,
        "expansion": null,
        "customIcon": null
      },
      "timestamp": 1770794883475
    },
    {
      "data": {
        "title": "ならず者",
        "description": "+1 カードを購入\n+$2\n他のプレイヤーは全員、自分の手札が3枚になるまで捨て札をする。\n-\nこのカードが場に出ているかぎり、あなたはカード1枚を購入するとき、+1%。",
        "type": "アクション-アタック",
        "type2": "",
        "price": "$6",
        "preview": "",
        "credit": "Illustration: Tu Pei-Shu",
        "creator": "© 2020 Rio Grande Games",
        "expansionName": "繁栄",
        "boldkeys": "",
        "deckSize": "",
        "size": "0",
        "color0": 0,
        "color1": 0,
        "traveller": "false",
        "trait": "false",
        "pictureX": "0",
        "pictureY": "0",
        "pictureZoom": "1",
        "picture": "https://wiki.dominionstrategy.com/images/8/83/GoonsArt.jpg",
        "expansion": "https://wiki.dominionstrategy.com/images/5/5e/Prosperity_old_icon.png",
        "customIcon": "",
        "edition": "【削除】",
        "official": true
      },
      "images": {
        "illustration": null,
        "expansion": null,
        "customIcon": null
      },
      "timestamp": 1770794883476
    }
  ]
}